pyscript/__init__.py
pyscript/cli.py
pyproject_script-0.0.0a1.dist-info/entry_points.txt
pyproject_script-0.0.0a1.dist-info/LICENSE
pyproject_script-0.0.0a1.dist-info/WHEEL
pyproject_script-0.0.0a1.dist-info/METADATA
pyproject_script-0.0.0a1.dist-info/RECORD
