Metadata-Version: 2.1
Name: pyproject-script
Version: 0.0.0a1
Summary: 
License: MIT
Author: Anthony Almarza
Author-email: anthony.almarza@gmail.com
Requires-Python: >=3.8,<4.0
Classifier: Development Status :: 3 - Alpha
Classifier: License :: OSI Approved :: MIT License
Classifier: Natural Language :: English
Classifier: Programming Language :: Python :: 3
Classifier: Programming Language :: Python :: 3 :: Only
Classifier: Programming Language :: Python :: 3.8
Classifier: Programming Language :: Python :: 3.9
Classifier: Topic :: Software Development :: Libraries :: Python Modules
Requires-Dist: toml (>=0.10.2,<0.11.0)
